model/__init__.py
model/dto.py
model/models.py
repository/__init__.py
repository/base.py
service/__init__.py
service/base.py
util/__init__.py
util/database.py
libherorafael-0.1.1.dist-info/METADATA
libherorafael-0.1.1.dist-info/WHEEL
libherorafael-0.1.1.dist-info/top_level.txt
libherorafael-0.1.1.dist-info/RECORD
