Metadata-Version: 2.4
Name: libherorafael
Version: 0.1.1
Summary: atividade lib hero .
Home-page: https://github.com/RafaelDeps/Projeto_de_sistemas/tree/main/atividade_hero_lib
Author: Rafael Deps 
Author-email: rafaeldeps15@gmail.com
Classifier: Programming Language :: Python :: 3
Classifier: License :: OSI Approved :: MIT License
Classifier: Operating System :: OS Independent
Requires-Python: >=3.8
Dynamic: author
Dynamic: author-email
Dynamic: classifier
Dynamic: description-content-type
Dynamic: home-page
Dynamic: requires-python
Dynamic: summary
